cdp/.python-version
cdp/__init__.py
cdp/__version__.py
cdp/analytics.py
cdp/api_clients.py
cdp/base_node_rpc_url.py
cdp/cdp_client.py
cdp/constants.py
cdp/end_user_account.py
cdp/end_user_client.py
cdp/errors.py
cdp/evm_call_types.py
cdp/evm_client.py
cdp/evm_local_account.py
cdp/evm_message_types.py
cdp/evm_server_account.py
cdp/evm_smart_account.py
cdp/evm_token_balances.py
cdp/evm_transaction_types.py
cdp/export.py
cdp/network_capabilities.py
cdp/network_config.py
cdp/network_scoped_evm_server_account.py
cdp/network_scoped_evm_smart_account.py
cdp/policies_client.py
cdp/solana_account.py
cdp/solana_client.py
cdp/solana_token_balances.py
cdp/update_account_types.py
cdp/update_smart_account_types.py
cdp/utils.py
cdp/actions/util.py
cdp/actions/evm/list_token_balances.py
cdp/actions/evm/request_faucet.py
cdp/actions/evm/send_transaction.py
cdp/actions/evm/send_user_operation.py
cdp/actions/evm/sign_and_wrap_typed_data_for_smart_account.py
cdp/actions/evm/wait_for_user_operation.py
cdp/actions/evm/spend_permissions/__init__.py
cdp/actions/evm/spend_permissions/account_use.py
cdp/actions/evm/spend_permissions/smart_account_use.py
cdp/actions/evm/swap/__init__.py
cdp/actions/evm/swap/create_swap_quote.py
cdp/actions/evm/swap/get_swap_price.py
cdp/actions/evm/swap/send_swap_operation.py
cdp/actions/evm/swap/send_swap_transaction.py
cdp/actions/evm/swap/types.py
cdp/actions/evm/transfer/__init__.py
cdp/actions/evm/transfer/account_transfer_strategy.py
cdp/actions/evm/transfer/constants.py
cdp/actions/evm/transfer/smart_account_transfer_strategy.py
cdp/actions/evm/transfer/transfer.py
cdp/actions/evm/transfer/types.py
cdp/actions/evm/transfer/utils.py
cdp/actions/solana/constants.py
cdp/actions/solana/request_faucet.py
cdp/actions/solana/send_transaction.py
cdp/actions/solana/sign_message.py
cdp/actions/solana/sign_transaction.py
cdp/actions/solana/transfer.py
cdp/actions/solana/types.py
cdp/actions/solana/utils.py
cdp/auth/README.md
cdp/auth/__init__.py
cdp_sdk-1.39.0.dist-info/METADATA
cdp_sdk-1.39.0.dist-info/WHEEL
cdp_sdk-1.39.0.dist-info/entry_points.txt
cdp_sdk-1.39.0.dist-info/RECORD
