Metadata-Version: 2.4
Name: cdp-sdk
Version: 1.39.0
Summary: CDP SDK
License: MIT
Requires-Python: >=3.10
Requires-Dist: aiohttp-retry>=2.9.1
Requires-Dist: aiohttp>=3.11.16
Requires-Dist: base58>=2.1.1
Requires-Dist: cryptography>=42.0.0
Requires-Dist: nest-asyncio<2,>=1.6.0
Requires-Dist: pydantic>=2.10.3
Requires-Dist: pyjwt>=2.10.1
Requires-Dist: python-dateutil>=2.9.0
Requires-Dist: solana>=0.36.6
Requires-Dist: solders>=0.26.0
Requires-Dist: urllib3>=2.2.3
Requires-Dist: web3<=7.10.0,>=7.6.0
Provides-Extra: dev
Requires-Dist: myst-parser>=4.0.1; extra == 'dev'
Requires-Dist: pytest-asyncio>=0.26.0; extra == 'dev'
Requires-Dist: pytest-cov>=4.1.0; extra == 'dev'
Requires-Dist: pytest>=8.0.0; extra == 'dev'
Requires-Dist: python-dotenv>=1.0.0; extra == 'dev'
Requires-Dist: pyyaml>=6.0; extra == 'dev'
Requires-Dist: ruff<0.8,>=0.7.1; extra == 'dev'
Requires-Dist: sphinx-autobuild>=2024.10.3; extra == 'dev'
Requires-Dist: sphinx-autodoc-typehints>=3.0.1; extra == 'dev'
Requires-Dist: sphinx>=8.1.3; extra == 'dev'
Requires-Dist: sphinxcontrib-napoleon>=0.7; extra == 'dev'
Requires-Dist: towncrier<25,>=24.8.0; extra == 'dev'
